django_model_snapshots/__init__.py
django_model_snapshots/admin.py
django_model_snapshots/context.py
django_model_snapshots/core.py
django_model_snapshots/managers.py
django_model_snapshots/mixins.py
django_model_snapshots/signals.py
django_model_snapshots/utils.py
django_model_snapshots/templates/admin/django_model_snapshots/history.html
django_model_snapshots-0.1.0.dist-info/METADATA
django_model_snapshots-0.1.0.dist-info/WHEEL
django_model_snapshots-0.1.0.dist-info/licenses/LICENSE
django_model_snapshots-0.1.0.dist-info/RECORD
