Metadata-Version: 2.4
Name: django-model-snapshots
Version: 0.1.0
Summary: A robust, elegant and ultra-performance Django model versioning package for Django 4.x+
Project-URL: Homepage, https://github.com/jotauses/django-model-snapshots
Project-URL: Documentation, https://jotauses.github.io/django-model-snapshots/
Project-URL: Bug Tracker, https://github.com/jotauses/django-model-snapshots/issues
Author-email: Joaquín Vázquez <jota.dev.es@gmail.com>
License: MIT
License-File: LICENSE
Classifier: Development Status :: 5 - Production/Stable
Classifier: Framework :: Django
Classifier: Framework :: Django :: 4.2
Classifier: Framework :: Django :: 5.0
Classifier: Framework :: Django :: 5.1
Classifier: Framework :: Django :: 5.2
Classifier: Intended Audience :: Developers
Classifier: License :: OSI Approved :: MIT License
Classifier: Programming Language :: Python :: 3
Classifier: Programming Language :: Python :: 3.10
Classifier: Programming Language :: Python :: 3.11
Classifier: Programming Language :: Python :: 3.12
Classifier: Programming Language :: Python :: 3.13
Classifier: Programming Language :: Python :: 3.14
Classifier: Topic :: Software Development :: Libraries :: Application Frameworks
Requires-Python: >=3.10
Requires-Dist: django>=4.2
Provides-Extra: test
Requires-Dist: psycopg2-binary; extra == 'test'
Requires-Dist: pytest; extra == 'test'
Requires-Dist: pytest-django; extra == 'test'
